queue_tee_pie/__init__.py
queue_tee_pie/core.py
queue_tee_pie/docs/api_reference.md
queue_tee_pie/docs/index.md
queue_tee_pie/docs/usage.md
queue_tee_pie/queue_tee_pie/__init__.py
queue_tee_pie/queue_tee_pie/storage/__init__.py
queue_tee_pie/queue_tee_pie/storage/sqlite_storage.py
queue_tee_pie/queue_tee_pie/utils/__init__.py
queue_tee_pie/queue_tee_pie/utils/logger.py
queue_tee_pie/queue_tee_pie/utils/serializer.py
queue_tee_pie/queue_tee_pie/workers/__init__.py
queue_tee_pie/queue_tee_pie/workers/worker.py
queue_tee_pie/tests/__init__.py
queue_tee_pie/tests/test_core.py
queue_tee_pie/tests/test_storage.py
queue_tee_pie/tests/test_worker.py
queue_tee_pie-0.1.0.dist-info/LICENSE
queue_tee_pie-0.1.0.dist-info/METADATA
queue_tee_pie-0.1.0.dist-info/WHEEL
queue_tee_pie-0.1.0.dist-info/RECORD
