Metadata-Version: 2.1
Name: queue_tee_pie
Version: 0.1.0
Summary: A lightweight background task library in Python.
Home-page: https://github.com/k4rimDev/QueueTeePie
License: Apache
Keywords: task,queue,background,tasks,async
Author: karim06-byte
Author-email: dev8@airgroup.az
Requires-Python: >=3.10,<4.0
Classifier: License :: Other/Proprietary License
Classifier: Programming Language :: Python :: 3
Classifier: Programming Language :: Python :: 3.10
Classifier: Programming Language :: Python :: 3.11
Classifier: Programming Language :: Python :: 3.12
Project-URL: Repository, https://github.com/k4rimDev/QueueTeePie
